SHICTHRSLogCore/__init__.py
SHICTHRSLogCore/utils/__init__.py
SHICTHRSLogCore/utils/config/SHRLogCore_readConfigFile.py
SHICTHRSLogCore/utils/config/SHRLogCore_readConfigFileBase.py
SHICTHRSLogCore/utils/config/SHRLogCore_writeConfigFile.py
SHICTHRSLogCore/utils/config/__init__.py
SHICTHRSLogCore/utils/hash/SHRLogCore_getHashCode.py
SHICTHRSLogCore/utils/hash/__init__.py
SHICTHRSLogCore/utils/time/SHRLogCore_pytzTimeSynchronizer.py
SHICTHRSLogCore/utils/time/__init__.py
shicthrslogcore-1.2.0.dist-info/METADATA
shicthrslogcore-1.2.0.dist-info/WHEEL
shicthrslogcore-1.2.0.dist-info/top_level.txt
shicthrslogcore-1.2.0.dist-info/RECORD
