Metadata-Version: 2.4
Name: SHICTHRSLogCore
Version: 1.2.0
Summary: SHICTHRS LOG CORE logging system
Home-page: https://github.com/JNTMTMTM/SHICTHRS_LogCore
Author: SHICTHRS
Author-email: contact@shicthrs.com
License: GPL-3.0
Requires-Dist: colorama==0.4.6
Requires-Dist: pytz==2025.2
Dynamic: author
Dynamic: author-email
Dynamic: home-page
Dynamic: license
Dynamic: requires-dist
Dynamic: summary
